promptblock/__init__.py
promptblock/client.py
promptblock-0.6.dist-info/METADATA
promptblock-0.6.dist-info/WHEEL
promptblock-0.6.dist-info/top_level.txt
promptblock-0.6.dist-info/RECORD
