Metadata-Version: 2.1
Name: promptblock
Version: 0.6
Summary: Client for Prompt Block. Build your prompt library with ease.
Author: Contentify
Author-email: hi@contentify.app
Requires-Dist: requests
